bohr_solver/__init__.py
bohr_solver/atom.py
bohr_solver/calculations.py
bohr_solver/visualization.py
bohr_solver-0.1.0.dist-info/licenses/LICENSE
bohr_solver-0.1.0.dist-info/METADATA
bohr_solver-0.1.0.dist-info/WHEEL
bohr_solver-0.1.0.dist-info/top_level.txt
bohr_solver-0.1.0.dist-info/RECORD
