Metadata-Version: 2.4
Name: bohr_solver
Version: 0.1.0
Summary: A Python library for simulating Bohr atoms
Author-email: Sebastian Rodriguez Garcia <sebrodriguezg@udistrital.edu.co>, Julian Leonardo Avila Martinez <jlavilam@udistrital.edu.co>, Camilo Andres Huertas Archila <cahuertasa@udistrital.edu.co>
License: MIT License
Project-URL: Homepage, https://github.com/Sebrodriguezg/BohrSolver
Requires-Python: >=3.8
License-File: LICENSE
Requires-Dist: numpy
Requires-Dist: matplotlib
Requires-Dist: seaborn
Requires-Dist: plotly
Dynamic: license-file
